git_service_cython.cp312-win_amd64.pyd
pygitzen/__init__.py
pygitzen/__main__.py
pygitzen/app.py
pygitzen/git_graph.py
pygitzen/git_service.py
pygitzen/git_watcher.py
pygitzen/config/__init__.py
pygitzen/config/keybindings.py
pygitzen/handlers/__init__.py
pygitzen/handlers/branch_actions.py
pygitzen/handlers/commit_actions.py
pygitzen/handlers/file_actions.py
pygitzen/handlers/stash_actions.py
pygitzen/handlers/sync_actions.py
pygitzen/services/__init__.py
pygitzen/services/branch_service.py
pygitzen/services/commit_service.py
pygitzen/services/stash_service.py
pygitzen/services/sync_service.py
pygitzen/services/tag_service.py
pygitzen/styles/__init__.py
pygitzen/styles/app.tcss
pygitzen/styles/dialogs.tcss
pygitzen/ui/__init__.py
pygitzen/ui/dialogs.py
pygitzen/ui/panes.py
pygitzen-0.2.6.dist-info/licenses/LICENSE
pygitzen-0.2.6.dist-info/METADATA
pygitzen-0.2.6.dist-info/WHEEL
pygitzen-0.2.6.dist-info/entry_points.txt
pygitzen-0.2.6.dist-info/top_level.txt
pygitzen-0.2.6.dist-info/RECORD
